suade_reverse_repo/__init__.py
suade_reverse_repo/core/__init__.py
suade_reverse_repo/core/repo/__init__.py
suade_reverse_repo/core/repo/reverse_repo_leg.py
suade_reverse_repo/core/repo/reverse_repo_transaction.py
suade_reverse_repo/core/repo/risk_factors.py
suade_reverse_repo/core/security/__init__.py
suade_reverse_repo/core/security/ifr_asset_type.py
suade_reverse_repo/core/security/security.py
suade_reverse_repo/core/security/volatility_adjustment_table.csv
suade_reverse_repo/data/__init__.py
suade_reverse_repo/models/__init__.py
suade_reverse_repo/models/repo_transaction.py
suade_reverse_repo-0.1.4.dist-info/WHEEL
suade_reverse_repo-0.1.4.dist-info/METADATA
suade_reverse_repo-0.1.4.dist-info/RECORD
