Metadata-Version: 2.1
Name: suade-reverse-repo
Version: 0.1.4
Summary: This package includes classes to model reverse repo transactions and calculate the associated ktcd factor.
Author: Moe Bourji
Author-email: mrbourji@gmail.com
Requires-Python: >=3.8,<3.9
Classifier: Programming Language :: Python :: 3
Classifier: Programming Language :: Python :: 3.8
Requires-Dist: atomicwrites (==1.4.0)
Requires-Dist: attrs (==21.2.0)
Requires-Dist: colorama (==0.4.4)
Requires-Dist: iniconfig (==1.1.1)
Requires-Dist: numpy (==1.21.2)
Requires-Dist: packaging (==21.0)
Requires-Dist: pandas (>=1.3.3,<2.0.0)
Requires-Dist: pluggy (==1.0.0)
Requires-Dist: py (==1.10.0)
Requires-Dist: pydantic (>=1.8.2,<2.0.0)
Requires-Dist: pyparsing (==2.4.7)
Requires-Dist: pytest (>=6.2.5,<7.0.0)
Requires-Dist: pytz (==2021.1)
Requires-Dist: six (==1.16.0)
Requires-Dist: toml (==0.10.2)
Requires-Dist: typing-extensions (>=3.10.0,<4.0.0)
